rbtoolz/__init__.py
rbtoolz/plotting.py
rbtoolz-1.4.1.dist-info/LICENSE
rbtoolz-1.4.1.dist-info/METADATA
rbtoolz-1.4.1.dist-info/WHEEL
rbtoolz-1.4.1.dist-info/top_level.txt
rbtoolz-1.4.1.dist-info/RECORD
