Metadata-Version: 2.1
Name: rbtoolz
Version: 1.4.1
Summary: Python-Pandas Postprocessing Library
Author: Ross Bonallo
Author-email: rossbonallo@gmail.com
Classifier: Programming Language :: Python :: 3
Classifier: License :: OSI Approved :: MIT License
Classifier: Operating System :: OS Independent
Requires-Python: >=3.10
License-File: LICENSE
Requires-Dist: numpy
Requires-Dist: pandas
Requires-Dist: plotly
Requires-Dist: kaleido
